cmdhelper.py
cmdhelper-0.4.0.dist-info/licenses/LICENSE
cmdhelper-0.4.0.dist-info/METADATA
cmdhelper-0.4.0.dist-info/WHEEL
cmdhelper-0.4.0.dist-info/top_level.txt
cmdhelper-0.4.0.dist-info/RECORD
