Metadata-Version: 2.4
Name: cmdhelper
Version: 0.4.0
Summary: Python utility for writing command line scripts with consistent look and feel.
Author-email: Juerg Beringer <juerg.beringer@gmail.com>
License-Expression: MIT
Project-URL: Homepage, https://github.com/juergberinger/cmdhelper
Keywords: command line utility,scripts
Classifier: Development Status :: 5 - Production/Stable
Classifier: Environment :: Console
Classifier: Intended Audience :: Developers
Classifier: Programming Language :: Python :: 3
Classifier: Programming Language :: Python :: 3.6
Classifier: Programming Language :: Python :: 3.7
Classifier: Programming Language :: Python :: 3.8
Classifier: Programming Language :: Python :: 3.9
Classifier: Programming Language :: Python :: 3.10
Classifier: Programming Language :: Python :: 3.11
Classifier: Programming Language :: Python :: 3.12
Classifier: Programming Language :: Python :: 3.13
Classifier: Topic :: System :: Shells
Classifier: Topic :: Utilities
Requires-Python: >=3.6
License-File: LICENSE
Dynamic: license-file
